{
    "signup": {
        "name": "Mirella Favaretto",
        "cpf": "41340033300",
        "email": "mirella@gmail.com",
        "whatsapp": "999999999",
        "address": {
            "postalcode": "04534011",
            "street": "Rua Joaquim Floriano",
            "number": "1000",
            "details": "Ap 142",
            "district": "Itaim Bibi",
            "city_state": "São Paulo/SP"
        },
        "delivery_method": "Moto",
        "cnh": "cnh-digital.jpg"
    },
    "cpf_inv": {
        "name": "Tamires Zanfolin",
        "cpf": "xx41340033300xx",
        "email": "tamires@gmail.com",
        "whatsapp": "888888888",
        "address": {
            "postalcode": "04534011",
            "street": "Rua Joaquim Floriano",
            "number": "1000",
            "details": "Ap 142",
            "district": "Itaim Bibi",
            "city_state": "São Paulo/SP"
        },
        "delivery_method": "Moto",
        "cnh": "cnh-digital.jpg"
    },

    "email_inv": {
        "name": "Tamires Zanfolin",
        "cpf": "41340033300",
        "email": "tamires.com.br",
        "whatsapp": "888888888",
        "address": {
            "postalcode": "04534011",
            "street": "Rua Joaquim Floriano",
            "number": "1000",
            "details": "Ap 142",
            "district": "Itaim Bibi",
            "city_state": "São Paulo/SP"
        },
        "delivery_method": "Moto",
        "cnh": "cnh-digital.jpg"
    }
}